expectations/__init__.py
expectations/core.py
expectations-1.0.0.dist-info/WHEEL
expectations-1.0.0.dist-info/METADATA
expectations-1.0.0.dist-info/RECORD
