Metadata-Version: 2.1
Name: expectations
Version: 1.0.0
Summary: Asynchronous expectations (Jobs/tasks) for future events.
Home-page: https://localhost
License: MIT
Keywords: expectations,expect,python,asyncio,async,asynchronous,jobs,tasks,future
Author: TensorTom
Author-email: 14287229+TensorTom@users.noreply.github.com
Maintainer: TensorTom
Maintainer-email: 14287229+TensorTom@users.noreply.github.com
Requires-Python: >=3.9,<4.0
Classifier: License :: OSI Approved :: MIT License
Classifier: Programming Language :: Python :: 3
Classifier: Programming Language :: Python :: 3.9
Requires-Dist: aiojobs (<1.0)
Project-URL: Repository, https://localhost
